otlp_psqlpy/__init__.py
otlp_psqlpy/package.py
otlp_psqlpy/py.typed
otlp_psqlpy/version.py
otlp_psqlpy-0.2.2.dist-info/METADATA
otlp_psqlpy-0.2.2.dist-info/WHEEL
otlp_psqlpy-0.2.2.dist-info/licenses/LICENSE
otlp_psqlpy-0.2.2.dist-info/RECORD
